{
  "name": "Mighty Servant of Leuk-o",
  "type": "item",
  "source": "TCE",
  "rarity": "artifact",
  "value": "",
  "weight": "",
  "description": "Named for the warlord who infamously employed it, the {@creature Mighty Servant of Leuk-o|TCE} is a fantastically powerful, 10-foot-tall machine that turns into an animate construct when piloted. Crafted of a gleaming black alloy of unknown origin, the servant is often described as a combination of a disproportioned dwarf and an oversized beetle. The servant contains enough space for 1 ton of cargo and a crew compartment within, from which up to two Medium creatures can control it-and potentiall",
  "requires_attunement": true,
  "properties": []
}