{
  "name": "Outer Essence Shard (Good)",
  "type": "item",
  "source": "TCE",
  "rarity": "rare",
  "value": "",
  "weight": 1,
  "description": "This flickering crystal holds the essence of an Outer Plane. As an action, you can attach the shard to a Tiny object (such as a weapon or a piece of jewelry) or detach it. It falls off if your attunement to it ends. You can use the shard as a spellcasting focus while you hold or wear it.\nWhen you use a Metamagic option on a spell while you are holding or wearing the shard, you can use that property.\n{\"type\": \"entries\", \"name\": \"Property\", \"entries\": [\"You or one creature of your choice that you ",
  "requires_attunement": true,
  "properties": []
}