{
  "name": "Ring of Mind Shielding",
  "type": "item",
  "source": "XDMG",
  "rarity": "uncommon",
  "value": "",
  "weight": "",
  "description": "While wearing this ring, you are immune to magic that allows other creatures to read your thoughts, determine whether you are lying, know your alignment, or know your creature type. Creatures can telepathically communicate with you only if you allow it.\nYou can take a {@action Magic|XPHB} action to cause the ring to become imperceptible until you take another {@action Magic|XPHB} action to make it perceptible, until you remove the ring, or until you die.\nIf you die while wearing the ring, your s",
  "requires_attunement": true,
  "properties": []
}